urlobject/__init__.py
urlobject/compat.py
urlobject/netloc.py
urlobject/path.py
urlobject/ports.py
urlobject/query_string.py
urlobject/six.py
urlobject/urlobject.py
URLObject-2.3.4.dist-info/METADATA
URLObject-2.3.4.dist-info/RECORD
URLObject-2.3.4.dist-info/top_level.txt
URLObject-2.3.4.dist-info/WHEEL
