Metadata-Version: 1.3
Name: URLObject
Version: 2.3.4
Summary: A utility class for manipulating URLs.
Home-page: http://github.com/zacharyvoase/urlobject
Author: Zachary Voase
Author-email: z@zacharyvoase.com
License: UNKNOWN
Platform: UNKNOWN
